torchsift/__init__.py
torchsift/ransac.py
torchsift/sift.py
torchsift/utils.py
torchsift-0.1.0.dist-info/LICENSE
torchsift-0.1.0.dist-info/METADATA
torchsift-0.1.0.dist-info/WHEEL
torchsift-0.1.0.dist-info/top_level.txt
torchsift-0.1.0.dist-info/RECORD
