Metadata-Version: 2.1
Name: torchsift
Version: 0.1.0
Summary: A Pytorch implementation of sift brute-force matcher and RANSAC
Home-page: https://github.com/chengzegang/TorchSIFT
Author: Zegang Cheng
Author-email: Zegang Cheng <zc2309@nyu.edu>
License: MIT
Project-URL: Homepage, https://github.com/chengzegang/TorchSIFT
Project-URL: Bug Tracker, https://github.com/chengzegang/TorchSIFT/issues
Classifier: Programming Language :: Python :: 3
Classifier: License :: OSI Approved :: MIT License
Classifier: Operating System :: OS Independent
Requires-Python: >=3.8
License-File: LICENSE
Requires-Dist: torch (>=1.12.1)
Requires-Dist: torchvision (>=0.13.1)
Requires-Dist: numpy
Requires-Dist: Pillow
Requires-Dist: opencv-python
Requires-Dist: setuptools
